koala_kafka/__init__.py
koala_kafka/kafka_schema_reader.py
koala_kafka/exceptions/__init__.py
koala_kafka/exceptions/exceptions.py
tests/__init__.py
tests/koala_kafka/__init__.py
tests/koala_kafka/test_kafka_schema_reader.py
tests/test_utils/__init__.py
tests/test_utils/constants.py
tests/test_utils/mock_http_response.py
koala_kafka-0.0.2.dist-info/METADATA
koala_kafka-0.0.2.dist-info/WHEEL
koala_kafka-0.0.2.dist-info/top_level.txt
koala_kafka-0.0.2.dist-info/RECORD
