Metadata-Version: 2.1
Name: koala-kafka
Version: 0.0.2
Summary: Kafka schema registry reader for nada-koala
Home-page: UNKNOWN
Author: NAV IKT
License: MIT
Project-URL: Bug Tracker, https://github.com/navikt
Project-URL: Documentation, https://github.com/navikt
Project-URL: Source Code, https://github.com/navikt
Platform: UNKNOWN
Classifier: Development Status :: 3 - Alpha
Classifier: License :: OSI Approved :: MIT License
Classifier: Programming Language :: Python :: 3.6
Classifier: Programming Language :: Python :: 3.7
Requires-Python: >=3.6
Requires-Dist: requests (>=2.23.0)
